OOPyGame/__init__.py
OOPyGame/colors.py
PyGameUI/__init__.py
PyGameUI/colors.py
OOPyGame-0.0.5.dist-info/LICENSE
OOPyGame-0.0.5.dist-info/LICENSE.md
OOPyGame-0.0.5.dist-info/METADATA
OOPyGame-0.0.5.dist-info/WHEEL
OOPyGame-0.0.5.dist-info/top_level.txt
OOPyGame-0.0.5.dist-info/RECORD
