Metadata-Version: 2.1
Name: OOPyGame
Version: 0.0.5
Summary: An object oriented python library for building user interfaces based on pygame
Home-page: https://github.com/ParisNeo/OOPyGame
Author: Saifeddine ALOUI
Author-email: aloui.saifeddine@gmail.com
License: UNKNOWN
Platform: UNKNOWN
Classifier: Programming Language :: Python :: 3.8
Classifier: License :: OSI Approved :: MIT License
Classifier: Operating System :: OS Independent
Requires-Dist: numpy
Requires-Dist: pygame
Provides-Extra: dev
